LICENSE
MANIFEST.in
setup.cfg
setup.py
macos_grok_overlay/.DS_Store
macos_grok_overlay/__init__.py
macos_grok_overlay/__main__.py
macos_grok_overlay/app.py
macos_grok_overlay/constants.py
macos_grok_overlay/health_checks.py
macos_grok_overlay/launcher.py
macos_grok_overlay/listener.py
macos_grok_overlay/main.py
macos_grok_overlay.egg-info/PKG-INFO
macos_grok_overlay.egg-info/SOURCES.txt
macos_grok_overlay.egg-info/dependency_links.txt
macos_grok_overlay.egg-info/entry_points.txt
macos_grok_overlay.egg-info/requires.txt
macos_grok_overlay.egg-info/top_level.txt
macos_grok_overlay/about/author.txt
macos_grok_overlay/about/classifiers.txt
macos_grok_overlay/about/description.txt
macos_grok_overlay/about/keywords.txt
macos_grok_overlay/about/on_pypi.txt
macos_grok_overlay/about/package_name.txt
macos_grok_overlay/about/requirements.txt
macos_grok_overlay/about/version.txt
macos_grok_overlay/about/version_history.md
macos_grok_overlay/logo/.DS_Store
macos_grok_overlay/logo/icon.icns
macos_grok_overlay/logo/logo_black.png
macos_grok_overlay/logo/logo_white.png
macos_grok_overlay/logo/icon.iconset/.DS_Store
macos_grok_overlay/logo/icon.iconset/icon_1200x1200.png
macos_grok_overlay/logo/icon.iconset/icon_128x128.png
macos_grok_overlay/logo/icon.iconset/icon_16x16.png
macos_grok_overlay/logo/icon.iconset/icon_256x256.png
macos_grok_overlay/logo/icon.iconset/icon_32x32.png
macos_grok_overlay/logo/icon.iconset/icon_512x512.png
macos_grok_overlay/logo/icon.iconset/icon_64x64.png