Metadata-Version: 2.2
Name: macos_grok_overlay
Version: 0.0.16
Summary: A simple macOS overlay application for pinning 'grok.com' to a dedicated window and key command.
Home-page: https://github.com/tchlux/macos_grok_overlay
Download-URL: https://github.com/tchlux/macos_grok_overlay/archive/0.0.16.tar.gz
Author: Thomas C.H. Lux
Author-email: thomas.ch.lux@gmail.com
License: MIT
Keywords: python3,grok,macos
Classifier: Operating System :: MacOS
Classifier: Development Status :: 5 - Production/Stable
Classifier: License :: OSI Approved :: MIT License
Classifier: Programming Language :: Python :: 3
Classifier: Programming Language :: Python :: 3.13
Requires-Python: >=3.10
License-File: LICENSE
Requires-Dist: pyobjc
Dynamic: author
Dynamic: author-email
Dynamic: classifier
Dynamic: download-url
Dynamic: home-page
Dynamic: keywords
Dynamic: license
Dynamic: requires-dist
Dynamic: requires-python
Dynamic: summary
